[
  {
    "category": "ข้อสอบเสมือนจริงปี 2567",
    "question": "การแบ่งหน่วยงานภายใน และการกำหนดท้องที่ของภาค สำนักงานอัยการสูงสุดต้องทำเป็นรูปแบบใด?",
    "options": [
      "1.กฎกระทรวง",
      "2.ประกาศ ก.อ.",
      "3.พระราชกฤษฎีกา",
      "4.ระเบียบสำนักงานอัยการสูงสุด"
    ],
    "answer": 2,
    "explanation": "การแบ่งหน่วยงาน จัดตั้งภาค และกำหนดอำนาจหน้าที่หน่วยงานภายใน ให้ทำเป็นประกาศ กอ"
  },
  {
    "category": "การใช้โปรแกรมในการปฏิบัติงาน",
    "question": "คำสั่ง “Save As” ใน Microsoft Word ใช้เพื่ออะไร",
    "options": [
      "1. บันทึกเอกสารเป็นไฟล์ใหม่โดยกำหนดชื่อและตำแหน่งใหม่",
      "2. บันทึกเอกสารลงในตำแหน่งเดิมทันที",
      "3. ล็อกเอกสารไม่ให้แก้ไข",
      "4. พิมพ์เอกสารออกมาเป็นกระดาษ"
    ],
    "answer": 1,
    "explanation": "“Save As” ใช้สำหรับสร้างไฟล์ใหม่จากเอกสารเดิม เหมาะสำหรับการเก็บไฟล์เวอร์ชันต่าง ๆ หรือการสร้างต้นฉบับใหม่โดยไม่แก้ไขไฟล์เดิม"
  },
  {
    "category": "พ.ร.บ. คุ้มครองข้อมูลส่วนบุคคล",
    "question": "พระราชบัญญัติคุ้มครองข้อมูลส่วนบุคคล พ.ศ. ๒๕๖๒ ใช้บังคับกับกรณีใดเป็นหลัก",
    "options": [
      "1. เฉพาะการเก็บข้อมูลโดยหน่วยงานของรัฐ",
      "2. การใช้ข้อมูลเพื่อการเรียนการสอนในครอบครัว",
      "3. การใช้ข้อมูลที่เป็นสาธารณะอยู่แล้ว",
      "4. การเก็บ ใช้ หรือเปิดเผยข้อมูลส่วนบุคคลของบุคคลที่อยู่ในราชอาณาจักร ไม่ว่าผู้ควบคุมหรือผู้ประมวลผลจะอยู่ภายในหรือนอกราชอาณาจักร"
    ],
    "answer": 4,
    "explanation": "กฎหมายครอบคลุมข้อมูลของบุคคลในไทย โดยไม่จำกัดว่าผู้ควบคุมอยู่ประเทศใด เป็นการคุ้มครองข้ามพรมแดน"
  },
  {
    "category": "พ.ร.บ. คุ้มครองข้อมูลส่วนบุคคล",
    "question": "ผู้ควบคุมข้อมูลส่วนบุคคลคือใคร",
    "options": [
      "1. เจ้าของข้อมูล",
      "2. บุคคลหรือนิติบุคคลที่มีอำนาจตัดสินใจเกี่ยวกับการเก็บ ใช้ หรือเปิดเผยข้อมูลส่วนบุคคล",
      "3. ผู้ประมวลผลที่ได้รับมอบหมาย",
      "4. หน่วยงานของรัฐที่ดูแลกฎหมาย"
    ],
    "answer": 2,
    "explanation": "ผู้ควบคุมคือผู้มีอำนาจในการตัดสินใจเกี่ยวกับวัตถุประสงค์และวิธีการประมวลผลข้อมูล"
  },
  {
    "category": "ระเบียบงานสารบรรณ",
    "question": "ข้อใด “ไม่ใช่องค์ประกอบบังคับ” ของแบบบันทึกข้อความ (หนังสือภายใน)",
    "options": [
      "1. ช่อง “ส่วนราชการ”",
      "2. คำลงท้ายแสดงความนับถือ",
      "3. ช่อง “เรื่อง”",
      "4. ช่อง “สิ่งที่ส่งมาด้วย”"
    ],
    "answer": 2,
    "explanation": "แบบบันทึกข้อความไม่มีการใช้คำลงท้ายแบบหนังสือภายนอก เช่น “ขอแสดงความนับถือ”)"
  },
  {
    "category": "ระเบียบงานสารบรรณ",
    "question": "หนังสือสั่งการประเภท “ระเบียบ” มีความหมายหลักคืออะไร",
    "options": [
      "1. กำหนดหลักเกณฑ์ วิธีปฏิบัติให้ถือปฏิบัติเป็นการทั่วไป",
      "2. เป็นแนวทางการเผยแพร่ข้อมูลสู่สาธารณะ",
      "3. เป็นคำสั่งที่ออกเป็นกรณีเฉพาะ",
      "4. เป็นหนังสือประชาสัมพันธ์ภายในหน่วยงาน"
    ],
    "answer": 1,
    "explanation": "ระเบียบคือข้อความที่ผู้มีอำนาจหน้าที่วางไว้เป็นหลักการเพื่อให้ถือปฏิบัติเป็นการทั่วไป)"
  },
  {
    "category": "พ.ร.บ. ระเบียบข้าราชการพลเรือน",
    "question": "กรรมการ ก.พ.ค. มีวาระการดำรงตำแหน่งกี่ปี",
    "options": [
      "1. 6 ปีและดำรงตำแหน่งได้วาระเดียว",
      "2. 3 ปีทำงานได้ไม่จำกัดวาระ",
      "3. 6 ปีและดำรงตำแหน่งได้ 2 วาระ",
      "4. 4 ปีทำงานได้ 2 วาระ"
    ],
    "answer": 1,
    "explanation": "มีวาระ 6 ปี และเป็นได้เพียงวาระเดียวเพื่อความเป็นอิสระ)"
  },
 {
    "category": "พ.ร.บ. องค์กรอัยการและพนักงานอัยการ",
    "question": "พนักงานอัยการต้องพ้นจากตำแหน่งเมื่อสิ้นปีงบประมาณที่อายุครบเท่าใด",
    "options": [
      "1.65 ปีบริบูรณ์",
      "2.70 ปีบริบูรณ์",
      "3.75 ปีบริบูรณ์",
      "4.60 ปีบริบูรณ์"
    ],
    "answer": 2,
    "explanation": "พ้นจากราชการเมื่อสิ้นปีงบประมาณที่อายุครบ 70 ปี แต่จะต้องพ้นจากตำแหน่งบริหาร (ตำแหน่งที่ดำรงอยู่) เมื่อสิ้นปีงบประมาณที่อายุครบ 65 ปี เพื่อไปดำรงตำแหน่ง \"อัยการอาวุโส\" จนกว่าจะพ้นจากราชการ  (อ้างอิง: พ.ร.บ.ระเบียบข้าราชการฝ่ายอัยการฯ มาตรา 56 และ มาตรา 39 แก้ไขเพิ่มเติมโดยฉบับที่ 2 พ.ศ. 2560)"
  },
  {
    "category": "พ.ร.บ. องค์กรอัยการและพนักงานอัยการ",
    "question": "ตำแหน่งประธาน ก.อ. ได้มาโดยวิธีใด",
    "options": [
      "1.เป็นตำแหน่งโดยตำแหน่งของอัยการสูงสุด",
      "2.ได้รับเลือกจากพนักงานอัยการ",
      "3.นายกรัฐมนตรีแต่งตั้งจากผู้ทรงคุณวุฒิ",
      "4.พระมหากษัตริย์ทรงเลือก"
    ],
    "answer": 2,
    "explanation": "ได้มาจากการ \"เลือก\" จากผู้รับบำเหน็จหรือบำนาญที่เคยรับราชการเป็นข้าราชการอัยการในตำแหน่งไม่ต่ำกว่าอธิบดีอัยการหรือเทียบเท่า  (อ้างอิง: พ.ร.บ.ระเบียบข้าราชการฝ่ายอัยการฯ มาตรา 18 (1) แก้ไขเพิ่มเติมโดยฉบับที่ 3 พ.ศ. 2561)"
  },
  {
    "category": "พ.ร.บ. องค์กรอัยการและพนักงานอัยการ",
    "question": "คณะกรรมการอัยการ เรียกโดยย่อว่าอะไร",
    "options": [
      "1.คก.อ.",
      "2.กม.อ.",
      "3.ก.อ.",
      "4.ค.ก.อ."
    ],
    "answer": 3,
    "explanation": "เรียกโดยย่อว่า \"ก.อ.\"  (อ้างอิง: พ.ร.บ.ระเบียบข้าราชการฝ่ายอัยการฯ มาตรา 18)"
  },
